daltonapi/__init__.py
daltonapi/api.py
daltonapi/tools/__init__.py
daltonapi/tools/atomic_classes.py
daltonapi/tools/atomic_errors.py
daltonapi/tools/wax_classes.py
daltonapi-0.5.0.dist-info/LICENSE
daltonapi-0.5.0.dist-info/WHEEL
daltonapi-0.5.0.dist-info/METADATA
daltonapi-0.5.0.dist-info/RECORD
