Metadata-Version: 2.1
Name: daltonapi
Version: 0.5.0
Summary: Python wrapper for the AtomicAssets API
Home-page: https://github.com/stuckatsixpm/dalton
License: MIT
Keywords: wax,atomicassets,api,wrapper,dalton,nft
Author: stuckatsixpm
Author-email: stuckat6pm@gmail.com
Requires-Python: >=3.7,<4.0
Classifier: License :: OSI Approved :: MIT License
Classifier: Programming Language :: Python :: 3
Classifier: Programming Language :: Python :: 3.7
Classifier: Programming Language :: Python :: 3.8
Classifier: Programming Language :: Python :: 3.9
Requires-Dist: requests (>=2.25.1,<3.0.0)
Project-URL: Documentation, https://dalton.readthedocs.io/en/latest/
Project-URL: Repository, https://github.com/stuckatsixpm/dalton
